Workbook

Sheet Sales
A1: Date | B1: Product | C1: Quantity | D1: Price | E1: Dealer Price | F1: Margin | G1: Revenue
A2: 45017 | B2: Product-B | C2: 5 | D2: =LOOKUP(B2, Product!$A$2:$A$6,Product!$C$2:$C$6) -> 78000 | E2: =LOOKUP(B2, Product!$A$2:$A$6,Product!$D$2:$D$6) -> 56000 | F2: =D2-E2 -> 22000 | G2: =C2*F2 -> 110000
A3: 45031 | B3: Product-C | C3: 8 | D3: =LOOKUP(B3, Product!$A$2:$A$6,Product!$C$2:$C$6) -> 125000 | E3: =LOOKUP(B3, Product!$A$2:$A$6,Product!$D$2:$D$6) -> 98000 | F3: =D3-E3 -> 27000 | G3: =C3*F3 -> 216000
A4: 45047 | B4: Product-D | C4: 7 | D4: =LOOKUP(B4, Product!$A$2:$A$6,Product!$C$2:$C$6) -> 95000 | E4: =LOOKUP(B4, Product!$A$2:$A$6,Product!$D$2:$D$6) -> 78000 | F4: =D4-E4 -> 17000 | G4: =C4*F4 -> 119000
A5: 45061 | B5: Product-E | C5: 9 | D5: =LOOKUP(B5, Product!$A$2:$A$6,Product!$C$2:$C$6) -> 98000 | E5: =LOOKUP(B5, Product!$A$2:$A$6,Product!$D$2:$D$6) -> 70000 | F5: =D5-E5 -> 28000 | G5: =C5*F5 -> 252000
A6: 45078 | B6: Product-A | C6: 10 | D6: =LOOKUP(B6, Product!$A$2:$A$6,Product!$C$2:$C$6) -> 30000 | E6: =LOOKUP(B6, Product!$A$2:$A$6,Product!$D$2:$D$6) -> 26000 | F6: =D6-E6 -> 4000 | G6: =C6*F6 -> 40000
A7: 45092 | B7: Product-B | C7: 12 | D7: =LOOKUP(B7, Product!$A$2:$A$6,Product!$C$2:$C$6) -> 78000 | E7: =LOOKUP(B7, Product!$A$2:$A$6,Product!$D$2:$D$6) -> 56000 | F7: =D7-E7 -> 22000 | G7: =C7*F7 -> 264000
A8: 45108 | B8: Product-C | C8: 7 | D8: =LOOKUP(B8, Product!$A$2:$A$6,Product!$C$2:$C$6) -> 125000 | E8: =LOOKUP(B8, Product!$A$2:$A$6,Product!$D$2:$D$6) -> 98000 | F8: =D8-E8 -> 27000 | G8: =C8*F8 -> 189000
A9: 45122 | B9: Product-D | C9: 10 | D9: =LOOKUP(B9, Product!$A$2:$A$6,Product!$C$2:$C$6) -> 95000 | E9: =LOOKUP(B9, Product!$A$2:$A$6,Product!$D$2:$D$6) -> 78000 | F9: =D9-E9 -> 17000 | G9: =C9*F9 -> 170000
A10: 45139 | B10: Product-E | C10: 11 | D10: =LOOKUP(B10, Product!$A$2:$A$6,Product!$C$2:$C$6) -> 98000 | E10: =LOOKUP(B10, Product!$A$2:$A$6,Product!$D$2:$D$6) -> 70000 | F10: =D10-E10 -> 28000 | G10: =C10*F10 -> 308000
A11: 45153 | B11: Product-A | C11: 15 | D11: =LOOKUP(B11, Product!$A$2:$A$6,Product!$C$2:$C$6) -> 30000 | E11: =LOOKUP(B11, Product!$A$2:$A$6,Product!$D$2:$D$6) -> 26000 | F11: =D11-E11 -> 4000 | G11: =C11*F11 -> 60000
A12: 45170 | B12: Product-B | C12: 5 | D12: =LOOKUP(B12, Product!$A$2:$A$6,Product!$C$2:$C$6) -> 78000 | E12: =LOOKUP(B12, Product!$A$2:$A$6,Product!$D$2:$D$6) -> 56000 | F12: =D12-E12 -> 22000 | G12: =C12*F12 -> 110000
A13: 45184 | B13: Product-C | C13: 8 | D13: =LOOKUP(B13, Product!$A$2:$A$6,Product!$C$2:$C$6) -> 125000 | E13: =LOOKUP(B13, Product!$A$2:$A$6,Product!$D$2:$D$6) -> 98000 | F13: =D13-E13 -> 27000 | G13: =C13*F13 -> 216000
... A67: 46006 | B67: Product-B | C67: 34 | D67: =LOOKUP(B67, Product!$A$2:$A$6,Product!$C$2:$C$6) -> 78000 | E67: =LOOKUP(B67, Product!$A$2:$A$6,Product!$D$2:$D$6) -> 56000 | F67: =D67-E67 -> 22000 | G67: =C67*F67 -> 748000

Sheet Product
A1: Product | B1: Name | C1: Unit Price | D1: Dealer Price
A2: Product-A | B2: Motorola | C2: 30000 | D2: 26000
A3: Product-B | B3: Samsung | C3: 78000 | D3: 56000
A4: Product-C | B4: Apple | C4: 125000 | D4: 98000
A5: Product-D | B5: OnePlus | C5: 95000 | D5: 78000
A6: Product-E | B6: Google | C6: 98000 | D6: 70000

Sheet Target
A1: Financial Year | B1: Target Revenue | C1: Actual
A2: FY 2023-2024 | B2: 5000000 | C2: =SUM(Sales!G2:G25) -> 4815000
A3: FY 2024-2025 | B3: 6500000 | C3: =SUM(Sales!G26:G49) -> 6537000
A4: FY 2025-2026 | B4: 10000000 | C4: =SUM(Sales!G50:G67) -> 8091000
